{"stats":{"minecraft:dropped":{"minecraft:compass":2,"minecraft:rotten_flesh":2,"minecraft:written_book":3},"minecraft:broken":{"minecraft:iron_pickaxe":1},"minecraft:mined":{"minecraft:diamond_ore":42,"minecraft:redstone_ore":3,"minecraft:furnace":2,"minecraft:iron_ore":26,"minecraft:andesite":27,"minecraft:crafting_table":3,"minecraft:granite":19,"minecraft:grass":1,"minecraft:grass_block":1,"minecraft:oak_log":42,"minecraft:coal_ore":13,"minecraft:dirt":4,"minecraft:cobblestone":1,"minecraft:stone":279,"minecraft:sugar_cane":4,"minecraft:diorite":32,"minecraft:oak_leaves":15},"minecraft:crafted":{"minecraft:wooden_sword":1,"minecraft:oak_planks":80,"minecraft:diamond_helmet":1,"minecraft:diamond_leggings":1,"minecraft:diamond_pickaxe":1,"minecraft:crafting_table":2,"minecraft:stick":20,"minecraft:wooden_pickaxe":1,"minecraft:iron_pickaxe":1,"minecraft:iron_ingot":6,"minecraft:stone_pickaxe":1,"minecraft:wooden_axe":1,"minecraft:stone_sword":1,"minecraft:furnace":1,"minecraft:stone_axe":1,"minecraft:air":0,"minecraft:diamond_chestplate":1},"minecraft:custom":{"minecraft:time_since_rest":41399,"minecraft:interact_with_furnace":4,"minecraft:sprint_one_cm":3205,"minecraft:damage_taken":2884,"minecraft:walk_one_cm":39491,"minecraft:mob_kills":1,"minecraft:drop":6,"minecraft:damage_dealt":1928,"minecraft:interact_with_crafting_table":7,"minecraft:swim_one_cm":1737,"minecraft:fly_one_cm":53411,"minecraft:player_kills":6,"minecraft:play_one_minute":80103,"minecraft:crouch_one_cm":1068,"minecraft:deaths":12,"minecraft:sneak_time":459,"minecraft:walk_under_water_one_cm":11723,"minecraft:jump":494,"minecraft:leave_game":3,"minecraft:walk_on_water_one_cm":12077,"minecraft:time_since_death":41379,"minecraft:fall_one_cm":16638},"minecraft:killed_by":{"minecraft:player":6,"minecraft:drowned":1,"minecraft:zombie":3},"minecraft:picked_up":{"minecraft:crafting_table":3,"minecraft:andesite":27,"minecraft:oak_log":39,"minecraft:diorite":32,"minecraft:redstone":13,"minecraft:lily_of_the_valley":2,"minecraft:dirt":5,"minecraft:rotten_flesh":2,"minecraft:apple":1,"minecraft:diamond":42,"minecraft:granite":19,"minecraft:iron_ore":51,"minecraft:written_book":1,"minecraft:oak_sapling":1,"minecraft:sugar_cane":8,"minecraft:coal":36,"minecraft:cobblestone":278,"minecraft:furnace":2},"minecraft:used":{"minecraft:diamond_pickaxe":137,"minecraft:apple":1,"minecraft:stone_pickaxe":35,"minecraft:iron_pickaxe":250,"minecraft:wooden_pickaxe":27,"minecraft:stone_axe":3,"minecraft:cobblestone":2,"minecraft:lily_of_the_valley":1,"minecraft:written_book":1,"minecraft:crafting_table":4,"minecraft:furnace":2},"minecraft:killed":{"minecraft:zombie":1}},"DataVersion":2586}